odoo/addons/purchase_exception/README.rst
odoo/addons/purchase_exception/__init__.py
odoo/addons/purchase_exception/__manifest__.py
odoo/addons/purchase_exception/data/purchase_exception_data.xml
odoo/addons/purchase_exception/i18n/es.po
odoo/addons/purchase_exception/i18n/fr.po
odoo/addons/purchase_exception/i18n/purchase_exception.pot
odoo/addons/purchase_exception/models/__init__.py
odoo/addons/purchase_exception/models/purchase.py
odoo/addons/purchase_exception/static/description/icon.png
odoo/addons/purchase_exception/tests/__init__.py
odoo/addons/purchase_exception/tests/test_purchase_exception.py
odoo/addons/purchase_exception/views/purchase_view.xml
odoo/addons/purchase_exception/wizard/__init__.py
odoo/addons/purchase_exception/wizard/purchase_exception_confirm.py
odoo/addons/purchase_exception/wizard/purchase_exception_confirm_view.xml
odoo11_addon_purchase_exception-11.0.1.0.0.99.dev5.dist-info/METADATA
odoo11_addon_purchase_exception-11.0.1.0.0.99.dev5.dist-info/WHEEL
odoo11_addon_purchase_exception-11.0.1.0.0.99.dev5.dist-info/top_level.txt
odoo11_addon_purchase_exception-11.0.1.0.0.99.dev5.dist-info/RECORD
